{
  "_fv": 60,
  "_type": "achievement",
  "definition": {
    "achievementName": "The World",
    "achievementDescription": "Obtain The World",
    "achievementIcon": {
      "value": "CUSTOM:AchievementTheWorld"
    },
    "background": "Default",
    "disableDisplay": false,
    "showPopup": false,
    "announceToChat": false,
    "hideIfNotCompleted": false,
    "rewardLoot": [],
    "rewardRecipes": [],
    "rewardFunction": "No function",
    "rewardXP": 0,
    "achievementType": "task",
    "parent": {
      "value": "CUSTOM:TheFoolAchievement"
    },
    "triggerxml": "<?xml version=\"1.0\" encoding=\"UTF-8\" standalone=\"no\"?><xml xmlns=\"https://developers.google.com/blockly/xml\"><block deletable=\"false\" type=\"advancement_trigger\" x=\"40\" y=\"80\"><next><block type=\"custom_trigger\" x=\"30\" y=\"44\"/></next></block></xml>"
  }
}