{
	"format_version": "1.12.0",
	"minecraft:geometry": [
		{
			"description": {
				"identifier": "geometry.MohammedAvdol",
				"texture_width": 256,
				"texture_height": 256,
				"visible_bounds_width": 3,
				"visible_bounds_height": 4.5,
				"visible_bounds_offset": [0, 1.75, 0]
			},
			"bones": [
				{
					"name": "avdolbody",
					"pivot": [0, 12, 0]
				},
				{
					"name": "avdolhead",
					"parent": "avdolbody",
					"pivot": [0, 24, 0],
					"cubes": [
						{"origin": [-4, 24, -4], "size": [8, 8, 8], "uv": [0, 0]},
						{"origin": [-4, 31, -4.25], "size": [8, 1, 1], "uv": [71, 28]},
						{"origin": [-4, 25, 3.25], "size": [8, 7, 1], "uv": [67, 0]},
						{"origin": [0.60633, 23.09824, 2.66466], "size": [1, 1, 3], "pivot": [-0.62428, 22.52656, 6.74603], "rotation": [-36.28567, 14.26008, -10.25103], "uv": [18, 75]},
						{"origin": [-1.12428, 23.09824, 4.31807], "size": [1, 1, 3], "pivot": [-0.62428, 22.52656, 6.74603], "rotation": [-40.52368, -28.02432, 21.88151], "uv": [72, 49]},
						{"origin": [-1.12428, 23.09824, 6.17398], "size": [1, 1, 3], "pivot": [-0.62428, 22.52656, 6.74603], "rotation": [-80.52368, -28.02432, 21.88151], "uv": [48, 5]},
						{"origin": [-2.85488, 23.09824, 7.8274], "size": [1, 1, 3], "pivot": [-0.62428, 22.52656, 6.74603], "rotation": [-62.0889, -9.82979, -30.69695], "uv": [42, 22]},
						{"origin": [3.25, 30, -4], "size": [1, 2, 8], "uv": [16, 62]},
						{"origin": [3.25, 25, 2], "size": [1, 3, 2], "uv": [62, 38]},
						{"origin": [3.25, 26, 0], "size": [1, 3, 2], "uv": [55, 28]},
						{"origin": [3.25, 28, -3], "size": [1, 1, 3], "uv": [18, 82]},
						{"origin": [-4.25, 28, -3], "size": [1, 1, 3], "uv": [44, 76]},
						{"origin": [-4.25, 26, 0], "size": [1, 3, 2], "uv": [24, 0]},
						{"origin": [-4.25, 25, 2], "size": [1, 3, 2], "uv": [0, 28]},
						{"origin": [-4.25, 30, -4], "size": [1, 2, 8], "uv": [61, 10]},
						{"origin": [-4, 31.25, -4], "size": [8, 1, 8], "uv": [24, 8]},
						{"origin": [0.5, 31.5, -2.5], "size": [2, 3, 2], "pivot": [1.5, 33, -1.5], "rotation": [10, 0, 10], "uv": [90, 44]},
						{"origin": [-2.5, 31.5, -2.5], "size": [2, 3, 2], "pivot": [-1.5, 33, -1.5], "rotation": [10, 0, -10], "uv": [41, 90]},
						{"origin": [-2.5, 31.5, 0.5], "size": [2, 3, 2], "pivot": [-1.5, 33, 1.5], "rotation": [-10, 0, -10], "uv": [16, 62]},
						{"origin": [0.5, 31.5, 0.5], "size": [2, 3, 2], "pivot": [1.5, 33, 1.5], "rotation": [-10, 0, 10], "uv": [80, 89]},
						{"origin": [2.5, 30.9, -4.25], "size": [2, 3, 2], "pivot": [3.5, 32.4, -3.25], "rotation": [25, 0, 25], "uv": [12, 92]},
						{"origin": [-1, 31.25, -4.75], "size": [2, 3, 2], "pivot": [0, 32.75, -3.75], "rotation": [25, 0, 0], "uv": [88, 91]},
						{"origin": [2.75, 31.25, -1], "size": [2, 3, 2], "pivot": [3.75, 32.75, 0], "rotation": [0, 0, 25], "uv": [91, 25]},
						{"origin": [-4.75, 31.25, -1], "size": [2, 3, 2], "pivot": [-3.75, 32.75, 0], "rotation": [0, 0, -25], "uv": [91, 12]},
						{"origin": [-4.5, 30.9, -4.25], "size": [2, 3, 2], "pivot": [-3.5, 32.4, -3.25], "rotation": [25, 0, -25], "uv": [91, 19]},
						{"origin": [-4.5, 30.9, 2.25], "size": [2, 3, 2], "pivot": [-3.5, 32.4, 3.25], "rotation": [-25, 0, -25], "uv": [49, 90]},
						{"origin": [-1, 31.25, 2.75], "size": [2, 3, 2], "pivot": [0, 32.75, 3.75], "rotation": [-25, 0, 0], "uv": [90, 60]},
						{"origin": [2.5, 30.9, 2.25], "size": [2, 3, 2], "pivot": [3.5, 32.4, 3.25], "rotation": [-25, 0, 25], "uv": [90, 74]},
						{"origin": [-0.11754, 28.81263, -4.45604], "size": [5, 2, 9], "pivot": [0, 29.91984, 0.04396], "rotation": [-7.43656, 0.9762, 7.43656], "uv": [43, 38]},
						{"origin": [-0.05283, 29.51854, -4.45], "size": [5, 1, 9], "pivot": [0, 29.91984, 0.04396], "rotation": [-7.43656, -0.9762, -7.43656], "uv": [52, 28]},
						{"origin": [-4.88246, 28.81263, -4.45604], "size": [5, 2, 9], "pivot": [0, 29.91984, 0.04396], "rotation": [-7.43656, -0.9762, -7.43656], "uv": [42, 17]},
						{"origin": [-4.94717, 29.51854, -4.45], "size": [5, 1, 9], "pivot": [0, 29.91984, 0.04396], "rotation": [-7.43656, 0.9762, 7.43656], "uv": [48, 0]},
						{"origin": [3, 26, -2], "size": [1, 2, 2], "pivot": [4, 27, -2], "rotation": [0, 12.5, 0], "uv": [54, 78]},
						{"origin": [-4, 26, -2], "size": [1, 2, 2], "pivot": [-4, 27, -2], "rotation": [0, -12.5, 0], "uv": [28, 72]},
						{"origin": [-3.75, 27.9, -4.05], "size": [3, 1, 0], "pivot": [-2.5, 28.5, -4.05], "rotation": [0, 0, 5], "uv": [21, 24]},
						{"origin": [0.75, 27.9, -4.05], "size": [3, 1, 0], "pivot": [2.5, 28.5, -4.05], "rotation": [0, 0, -5], "uv": [24, 5]}
					]
				},
				{
					"name": "necklace",
					"parent": "avdolhead",
					"pivot": [0, 26.5, -1],
					"rotation": [-25, 0, 0],
					"cubes": [
						{"origin": [-1.53163, 21.12351, -2.2634], "size": [2, 2, 1], "pivot": [0, 20.04345, -3.16976], "rotation": [19.40047, -8.70871, 78.65236], "uv": [92, 86]},
						{"origin": [-1.5, 18.5, -3], "size": [3, 3, 1], "pivot": [0, 20.04345, -3.16976], "rotation": [25, 0, 0], "uv": [0, 21]},
						{"origin": [-1, 16, -2.999], "size": [2, 3, 1], "pivot": [0, 20.04345, -3.16976], "rotation": [25, 0, 0], "uv": [14, 33]},
						{"origin": [-1.2944, 22.9877, -3.37788], "size": [2, 2, 1], "pivot": [0, 20.04345, -3.16976], "rotation": [6.11456, 41.77574, 68.2467], "uv": [4, 93]},
						{"origin": [3.58106, 22.24924, -2.98032], "size": [2, 2, 1], "pivot": [3.41454, 23.48354, -2.17026], "rotation": [-18.07107, 9.70033, 19.38947], "uv": [70, 94]},
						{"origin": [3.54661, 23.4553, -2.15866], "size": [2, 2, 1], "pivot": [3.41454, 23.48354, -2.17026], "rotation": [-34.12878, 37.34874, -13.04328], "uv": [76, 94]},
						{"origin": [4.33379, 24.03096, -2.78508], "size": [2, 2, 1], "pivot": [3.41454, 23.48354, -2.17026], "rotation": [-25.25766, -11.2531, -29.97096], "uv": [82, 94]},
						{"origin": [-0.46837, 21.12351, -2.2634], "size": [2, 2, 1], "pivot": [0, 20.04345, -3.16976], "rotation": [19.40047, 8.70871, -78.65236], "uv": [47, 71]},
						{"origin": [-0.7056, 22.9877, -3.37788], "size": [2, 2, 1], "pivot": [0, 20.04345, -3.16976], "rotation": [6.11456, -41.77574, -68.2467], "uv": [52, 84]},
						{"origin": [-5.58106, 22.24924, -2.98032], "size": [2, 2, 1], "pivot": [-3.41454, 23.48354, -2.17026], "rotation": [-18.07107, -9.70033, -19.38947], "uv": [76, 84]},
						{"origin": [-5.54661, 23.4553, -2.15866], "size": [2, 2, 1], "pivot": [-3.41454, 23.48354, -2.17026], "rotation": [-34.12878, -37.34874, 13.04328], "uv": [20, 92]},
						{"origin": [-6.33379, 24.03096, -2.78508], "size": [2, 2, 1], "pivot": [-3.41454, 23.48354, -2.17026], "rotation": [-25.25766, 11.2531, 29.97096], "uv": [57, 92]}
					]
				},
				{
					"name": "avdoltorso",
					"parent": "avdolbody",
					"pivot": [0, 24, 0],
					"cubes": [
						{"origin": [-4, 12, -2], "size": [8, 12, 4], "uv": [28, 31]},
						{"origin": [-4, 14, -2.5], "size": [8, 1, 1], "uv": [71, 12]},
						{"origin": [3, 12, -2.4], "size": [1, 1, 1], "uv": [56, 71]},
						{"origin": [3.4, 12, -2], "size": [1, 1, 4], "uv": [85, 14]},
						{"origin": [-4, 11.75, -2], "size": [1, 1, 4], "uv": [85, 0]},
						{"origin": [3, 11.75, -2], "size": [1, 1, 4], "uv": [80, 84]},
						{"origin": [-4.4, 12, -2], "size": [1, 1, 4], "uv": [6, 85]},
						{"origin": [-4, 12, -2.4], "size": [1, 1, 1], "uv": [71, 32]},
						{"origin": [3, 12, 1.4], "size": [1, 1, 1], "uv": [48, 31]},
						{"origin": [-4, 12, 1.4], "size": [1, 1, 1], "uv": [53, 0]},
						{"origin": [-4, 13, -2.7], "size": [8, 1, 1], "uv": [71, 10]},
						{"origin": [-3, 12, -2.7], "size": [6, 1, 1], "uv": [76, 61]},
						{"origin": [-3, 12, 1.7], "size": [6, 1, 1], "uv": [76, 8]},
						{"origin": [-4, 13, 1.7], "size": [8, 1, 1], "uv": [62, 45]},
						{"origin": [3.7, 13, -2], "size": [1, 1, 4], "uv": [84, 76]},
						{"origin": [3.5, 14, -2], "size": [1, 1, 4], "uv": [70, 84]},
						{"origin": [-4.7, 13, -2], "size": [1, 1, 4], "uv": [84, 45]},
						{"origin": [-4.5, 14, -2], "size": [1, 1, 4], "uv": [84, 50]},
						{"origin": [-4, 14, 1.5], "size": [8, 1, 1], "uv": [70, 26]},
						{"origin": [-3, 11.65, -2], "size": [6, 1, 4], "uv": [48, 10]},
						{"origin": [-0.46688, 21.51986, -3.97], "size": [6, 3, 9], "pivot": [0.59238, 23.56096, 0.52157], "rotation": [14.65993, 3.21132, -12.08681], "uv": [21, 19]},
						{"origin": [-5.53312, 21.51986, -3.97843], "size": [6, 3, 9], "pivot": [-0.59238, 23.56096, 0.52157], "rotation": [14.65993, -3.21132, 12.08681], "uv": [0, 16]},
						{"origin": [-3.5, 19.60922, -2.91446], "size": [7, 2, 1], "uv": [12, 72]},
						{"origin": [-3.5, 18.86738, -2.75], "size": [7, 1, 1], "pivot": [-0.5, 19.36738, -2.25], "rotation": [25, 0, 0], "uv": [71, 47]},
						{"origin": [-4, 16.12553, -2.58554], "size": [8, 3, 1], "uv": [68, 65]},
						{"origin": [-4, 16.12553, 1.58554], "size": [8, 3, 1], "uv": [61, 20]},
						{"origin": [-4, 15.38369, -2.75], "size": [8, 1, 1], "pivot": [0, 15.88369, -2.25], "rotation": [-25, 0, 0], "uv": [71, 16]},
						{"origin": [-4, 14.9, -2.75], "size": [8, 1, 1], "pivot": [0, 15.4, -2.25], "rotation": [25, 0, 0], "uv": [71, 14]},
						{"origin": [-4, 14.9, 1.75], "size": [8, 1, 1], "pivot": [0, 15.4, 2.25], "rotation": [-25, 0, 0], "uv": [21, 17]},
						{"origin": [-4, 15.38369, 1.75], "size": [8, 1, 1], "pivot": [0, 15.88369, 2.25], "rotation": [25, 0, 0], "uv": [61, 24]},
						{"origin": [3.75, 14.9, -2], "size": [1, 1, 4], "pivot": [4.25, 15.4, 0], "rotation": [0, 0, 25], "uv": [40, 84]},
						{"origin": [3.75, 15.38369, -2], "size": [1, 1, 4], "pivot": [4.25, 15.88369, 0], "rotation": [0, 0, -25], "uv": [28, 84]},
						{"origin": [3.58554, 16.12553, -2], "size": [1, 3, 4], "uv": [68, 76]},
						{"origin": [-4.75, 14.9, -2], "size": [1, 1, 4], "pivot": [-4.25, 15.4, 0], "rotation": [0, 0, -25], "uv": [64, 83]},
						{"origin": [-4.75, 15.38369, -2], "size": [1, 1, 4], "pivot": [-4.25, 15.88369, 0], "rotation": [0, 0, 25], "uv": [54, 83]},
						{"origin": [-4.58554, 16.12553, -2], "size": [1, 3, 4], "uv": [76, 54]}
					]
				},
				{
					"name": "coat",
					"parent": "avdoltorso",
					"pivot": [0, 24, 0],
					"cubes": [
						{"origin": [-3.36237, 2.31825, 1.79], "size": [7, 21, 1], "pivot": [0, 22.94825, 2.295], "rotation": [2.46207, -0.43399, 9.99067], "uv": [44, 49]},
						{"origin": [-6.07187, 3.03865, -3.25], "size": [1, 21, 6], "pivot": [-4.97187, 13.53865, -0.25], "rotation": [0, 0, 10], "uv": [0, 28]},
						{"origin": [-5.07187, 3.03865, -3.25], "size": [1, 21, 1], "pivot": [-4.97187, 13.53865, -0.25], "rotation": [0, 0, 10], "uv": [60, 65]},
						{"origin": [-4.32187, 8.03865, -3.24], "size": [1, 1, 1], "pivot": [-4.97187, 13.53865, -0.25], "rotation": [0, 0, 10], "uv": [65, 16]},
						{"origin": [-4.07187, 3.03865, -3.25], "size": [1, 5, 1], "pivot": [-4.97187, 13.53865, -0.25], "rotation": [0, 0, 10], "uv": [68, 69]},
						{"origin": [-3.32187, 5.03865, -3.24], "size": [1, 1, 1], "pivot": [-4.97187, 13.53865, -0.25], "rotation": [0, 0, 10], "uv": [53, 5]},
						{"origin": [-3.07187, 3.03865, -3.25], "size": [1, 2, 1], "pivot": [-4.97187, 13.53865, -0.25], "rotation": [0, 0, 10], "uv": [5, 16]},
						{
							"origin": [-4.66771, 2.00554, -3.76],
							"size": [1, 9, 2],
							"pivot": [-4.16771, 6.50554, -3.26],
							"rotation": [0, 0, -10],
							"uv": {
								"north": {"uv": [38, 89], "uv_size": [1, 9]},
								"east": {"uv": [37, 89], "uv_size": [1, 9]},
								"south": {"uv": [40, 89], "uv_size": [1, 9]},
								"west": {"uv": [39, 89], "uv_size": [1, 9]},
								"up": {"uv": [38, 88], "uv_size": [1, 1]},
								"down": {"uv": [39, 89], "uv_size": [1, -1]}
							}
						},
						{
							"origin": [-3.72187, 19.28865, -3.75],
							"size": [1, 3, 2],
							"pivot": [-3.22187, 20.28865, -3.25],
							"rotation": [0, 0, -12.5],
							"uv": {
								"north": {"uv": [9, 29], "uv_size": [1, 3]},
								"east": {"uv": [8, 29], "uv_size": [1, 3]},
								"south": {"uv": [11, 29], "uv_size": [1, 3]},
								"west": {"uv": [10, 29], "uv_size": [1, 3]},
								"up": {"uv": [9, 28], "uv_size": [1, 1]},
								"down": {"uv": [10, 29], "uv_size": [1, -1]}
							}
						},
						{
							"origin": [3.66771, 2.00554, -3.76],
							"size": [1, 9, 2],
							"pivot": [4.16771, 6.50554, -3.26],
							"rotation": [0, 0, 10],
							"uv": {
								"north": {"uv": [67, 89], "uv_size": [1, 9]},
								"east": {"uv": [66, 89], "uv_size": [1, 9]},
								"south": {"uv": [69, 89], "uv_size": [1, 9]},
								"west": {"uv": [68, 89], "uv_size": [1, 9]},
								"up": {"uv": [67, 88], "uv_size": [1, 1]},
								"down": {"uv": [68, 89], "uv_size": [1, -1]}
							}
						},
						{
							"origin": [2.83009, 10.56435, -3.77],
							"size": [1, 9, 2],
							"pivot": [3.33009, 18.06435, -3.25],
							"rotation": [0, 0, -12.5],
							"uv": {
								"north": {"uv": [27, 90], "uv_size": [1, 9]},
								"east": {"uv": [26, 90], "uv_size": [1, 9]},
								"south": {"uv": [29, 90], "uv_size": [1, 9]},
								"west": {"uv": [28, 90], "uv_size": [1, 9]},
								"up": {"uv": [27, 89], "uv_size": [1, 1]},
								"down": {"uv": [28, 90], "uv_size": [1, -1]}
							}
						},
						{
							"origin": [-3.83009, 10.56435, -3.77],
							"size": [1, 9, 2],
							"pivot": [-3.33009, 18.06435, -3.25],
							"rotation": [0, 0, 12.5],
							"uv": {
								"north": {"uv": [1, 89], "uv_size": [1, 9]},
								"east": {"uv": [0, 89], "uv_size": [1, 9]},
								"south": {"uv": [3, 89], "uv_size": [1, 9]},
								"west": {"uv": [2, 89], "uv_size": [1, 9]},
								"up": {"uv": [1, 88], "uv_size": [1, 1]},
								"down": {"uv": [2, 89], "uv_size": [1, -1]}
							}
						},
						{
							"origin": [2.72187, 19.28865, -3.75],
							"size": [1, 3, 2],
							"pivot": [3.22187, 20.28865, -3.25],
							"rotation": [0, 0, 12.5],
							"uv": {
								"north": {"uv": [17, 29], "uv_size": [1, 3]},
								"east": {"uv": [16, 29], "uv_size": [1, 3]},
								"south": {"uv": [19, 29], "uv_size": [1, 3]},
								"west": {"uv": [18, 29], "uv_size": [1, 3]},
								"up": {"uv": [17, 28], "uv_size": [1, 1]},
								"down": {"uv": [18, 29], "uv_size": [1, -1]}
							}
						},
						{"origin": [5.07187, 3.03865, -3.25], "size": [1, 21, 6], "pivot": [4.97187, 13.53865, -0.25], "rotation": [0, 0, -10], "uv": [14, 31]},
						{"origin": [4.07187, 3.03865, -3.25], "size": [1, 21, 1], "pivot": [4.97187, 13.53865, -0.25], "rotation": [0, 0, -10], "uv": [64, 65]},
						{"origin": [2.07187, 3.03865, -3.25], "size": [1, 2, 1], "pivot": [4.97187, 13.53865, -0.25], "rotation": [0, 0, -10], "uv": [26, 19]},
						{"origin": [2.32187, 5.03865, -3.24], "size": [1, 1, 1], "pivot": [4.97187, 13.53865, -0.25], "rotation": [0, 0, -10], "uv": [0, 71]},
						{"origin": [3.07187, 3.03865, -3.25], "size": [1, 5, 1], "pivot": [4.97187, 13.53865, -0.25], "rotation": [0, 0, -10], "uv": [30, 89]},
						{"origin": [3.32187, 8.03865, -3.24], "size": [1, 1, 1], "pivot": [4.97187, 13.53865, -0.25], "rotation": [0, 0, -10], "uv": [71, 30]},
						{"origin": [-3.63763, 2.31825, 1.8], "size": [7, 21, 1], "pivot": [0, 22.94825, 2.295], "rotation": [2.46207, 0.43399, -9.99067], "uv": [28, 48]},
						{"origin": [3.75613, 21.20557, 1.05258], "size": [1, 2, 3], "pivot": [4.25613, 22.20557, 2.55258], "rotation": [12.28436, -37.17352, -20.18204], "uv": [42, 17]},
						{"origin": [-4.75613, 21.20557, 1.05258], "size": [1, 2, 3], "pivot": [-4.25613, 22.20557, 2.55258], "rotation": [12.28436, 37.17352, 20.18204], "uv": [21, 19]},
						{"origin": [-5.27786, 20.94024, -1.11822], "size": [1, 2, 3], "pivot": [-4.77786, 21.94024, 0.38178], "rotation": [10.08359, -14.46833, 10.14264], "uv": [0, 16]},
						{"origin": [4.27786, 20.94024, -1.11822], "size": [1, 2, 3], "pivot": [4.77786, 21.94024, 0.38178], "rotation": [10.08359, 14.46833, -10.14264], "uv": [0, 0]},
						{"origin": [-0.32842, 20.27541, 1.10171], "size": [4, 2, 3], "pivot": [0, 21.75683, 2.60171], "rotation": [9.76758, 2.15393, -12.31594], "uv": [42, 0]},
						{"origin": [-3.67158, 20.27541, 1.10171], "size": [4, 2, 3], "pivot": [0, 21.75683, 2.60171], "rotation": [9.76758, -2.15393, 12.31594], "uv": [36, 71]},
						{"origin": [-4, 4.12553, 2.05], "size": [8, 17, 1], "pivot": [0, 17.62553, 2.91446], "rotation": [2.5, 0, 0], "uv": [110, 0]}
					]
				},
				{
					"name": "avdolleft_arm",
					"parent": "avdolbody",
					"pivot": [5, 22, 0],
					"cubes": [
						{"origin": [4, 12, -2], "size": [4, 12, 4], "uv": [60, 49]},
						{"origin": [4, 13, -2.25], "size": [4, 1, 1], "uv": [70, 92]},
						{"origin": [4, 13, 1.25], "size": [4, 1, 1], "uv": [91, 2]},
						{"origin": [7.25, 13, -2], "size": [1, 1, 4], "uv": [86, 81]},
						{"origin": [3.75, 13, -2], "size": [1, 1, 4], "uv": [85, 20]},
						{"origin": [4, 14, -2.35], "size": [4, 1, 1], "uv": [90, 52]},
						{"origin": [7.35, 14, -2], "size": [1, 1, 4], "uv": [82, 40]},
						{"origin": [4, 14, 1.35], "size": [4, 1, 1], "uv": [91, 0]},
						{"origin": [3.65, 14, -2], "size": [1, 1, 4], "uv": [82, 65]},
						{"origin": [4, 15, -2.45], "size": [4, 1, 1], "uv": [56, 15]},
						{"origin": [7.45, 15, -2], "size": [1, 1, 4], "uv": [78, 30]},
						{"origin": [4, 15, 1.45], "size": [4, 1, 1], "uv": [90, 50]},
						{"origin": [3.55, 15, -2], "size": [1, 1, 4], "uv": [82, 35]},
						{"origin": [4, 20.22145, -2.82625], "size": [4, 2, 1], "pivot": [6, 21.22145, -2.32625], "rotation": [7.5, 0, 0], "uv": [4, 90]},
						{"origin": [4, 22.07382, -2.82625], "size": [4, 2, 1], "pivot": [6, 23.07382, -2.32625], "rotation": [-7.5, 0, 0], "uv": [70, 89]},
						{"origin": [7.82625, 22.07382, -2], "size": [1, 2, 4], "pivot": [8.32625, 23.07382, 0], "rotation": [0, 0, -7.5], "uv": [22, 82]},
						{"origin": [7.82625, 20.22145, -2], "size": [1, 2, 4], "pivot": [8.32625, 21.22145, 0], "rotation": [0, 0, 7.5], "uv": [12, 82]},
						{"origin": [4, 23.5, -2], "size": [4, 1, 4], "pivot": [6, 24, 0], "rotation": [0, 0, 2.5], "uv": [0, 71]},
						{"origin": [4, 20.22145, 1.82625], "size": [4, 2, 1], "pivot": [6, 21.22145, 2.32625], "rotation": [-7.5, 0, 0], "uv": [89, 9]},
						{"origin": [4, 22.07382, 1.82625], "size": [4, 2, 1], "pivot": [6, 23.07382, 2.32625], "rotation": [7.5, 0, 0], "uv": [88, 70]},
						{"origin": [3.17375, 22.07382, -2], "size": [1, 2, 4], "pivot": [3.67375, 23.07382, 0], "rotation": [0, 0, 7.5], "uv": [79, 18]},
						{"origin": [3.17375, 20.22145, -2], "size": [1, 2, 4], "pivot": [3.67375, 21.22145, 0], "rotation": [0, 0, -7.5], "uv": [6, 79]},
						{"origin": [4, 18.66734, -2.68815], "size": [4, 1, 1], "pivot": [6, 18.66734, -2.18815], "rotation": [12.5, 0, 0], "uv": [92, 68]},
						{"origin": [4, 16.93904, -2.94178], "size": [4, 2, 1], "pivot": [6, 17.93904, -2.44178], "rotation": [-15, 0, 0], "uv": [88, 65]},
						{"origin": [3, 15.93904, -3.29178], "size": [6, 1, 1], "pivot": [6, 17.93904, -2.44178], "rotation": [-15, 0, 0], "uv": [74, 76]},
						{"origin": [8.31237, 15.92201, -3], "size": [1, 1, 6], "pivot": [8.31237, 18.42201, 0], "rotation": [0, 0, -15], "uv": [28, 70]},
						{"origin": [4, 19.4272, -2.90459], "size": [4, 1, 1], "pivot": [6, 19.4272, -2.40459], "rotation": [-12.5, 0, 0], "uv": [92, 81]},
						{"origin": [4, 16.93904, 1.94178], "size": [4, 2, 1], "pivot": [6, 17.93904, 2.44178], "rotation": [15, 0, 0], "uv": [85, 5]},
						{"origin": [4, 18.66734, 1.68815], "size": [4, 1, 1], "pivot": [6, 18.66734, 2.18815], "rotation": [-12.5, 0, 0], "uv": [92, 55]},
						{"origin": [4, 19.4272, 1.90459], "size": [4, 1, 1], "pivot": [6, 19.4272, 2.40459], "rotation": [12.5, 0, 0], "uv": [92, 57]},
						{"origin": [3, 15.93904, 2.29178], "size": [6, 1, 1], "pivot": [6, 17.93904, 2.44178], "rotation": [15, 0, 0], "uv": [76, 63]},
						{"origin": [7.90459, 19.4272, -2], "size": [1, 1, 4], "pivot": [8.40459, 19.4272, 0], "rotation": [0, 0, -12.5], "uv": [86, 86]},
						{"origin": [7.68815, 18.66734, -2], "size": [1, 1, 4], "pivot": [8.18815, 18.66734, 0], "rotation": [0, 0, 12.5], "uv": [86, 55]},
						{"origin": [7.81237, 16.92201, -2], "size": [1, 2, 4], "pivot": [8.31237, 18.42201, 0], "rotation": [0, 0, -15], "uv": [78, 78]},
						{"origin": [2.68763, 15.92201, -3], "size": [1, 1, 6], "pivot": [3.68763, 18.42201, 0], "rotation": [0, 0, 15], "uv": [68, 69]},
						{"origin": [3.18763, 16.92201, -2], "size": [1, 2, 4], "pivot": [3.68763, 18.42201, 0], "rotation": [0, 0, 15], "uv": [48, 78]},
						{"origin": [3.31185, 18.66734, -2], "size": [1, 1, 4], "pivot": [3.81185, 18.66734, 0], "rotation": [0, 0, -12.5], "uv": [85, 26]},
						{"origin": [3.09541, 19.4272, -2], "size": [1, 1, 4], "pivot": [3.59541, 19.4272, 0], "rotation": [0, 0, 12.5], "uv": [46, 85]},
						{"origin": [7.86646, 16.73995, -2.84178], "size": [1, 3, 1], "pivot": [8.26646, 17.73995, -2.44178], "rotation": [-15, 0, -15], "uv": [64, 10]},
						{"origin": [6.86646, 16.73995, -2.84178], "size": [1, 1, 0], "pivot": [8.26646, 17.73995, -2.44178], "rotation": [-15, 0, -15], "uv": [0, 17]},
						{"origin": [8.86646, 16.73995, -1.84178], "size": [0, 1, 1], "pivot": [8.26646, 17.73995, -2.44178], "rotation": [-15, 0, -15], "uv": [5, 1]},
						{"origin": [6.86646, 16.73995, 2.84178], "size": [1, 1, 0], "pivot": [8.26646, 17.73995, 2.44178], "rotation": [15, 0, -15], "uv": [0, 16]},
						{"origin": [7.86646, 16.73995, 1.84178], "size": [1, 3, 1], "pivot": [8.26646, 17.73995, 2.44178], "rotation": [15, 0, -15], "uv": [60, 49]},
						{"origin": [8.86646, 16.73995, 0.84178], "size": [0, 1, 1], "pivot": [8.26646, 17.73995, 2.44178], "rotation": [15, 0, -15], "uv": [5, 0]},
						{"origin": [4.13354, 16.73995, 2.84178], "size": [1, 1, 0], "pivot": [3.73354, 17.73995, 2.44178], "rotation": [15, 0, 15], "uv": [0, 0]},
						{"origin": [3.13354, 16.73995, 1.84178], "size": [1, 3, 1], "pivot": [3.73354, 17.73995, 2.44178], "rotation": [15, 0, 15], "uv": [48, 10]},
						{"origin": [3.13354, 16.73995, 0.84178], "size": [0, 1, 1], "pivot": [3.73354, 17.73995, 2.44178], "rotation": [15, 0, 15], "uv": [0, 0]},
						{"origin": [4.13354, 16.73995, -2.84178], "size": [1, 1, 0], "pivot": [3.73354, 17.73995, -2.44178], "rotation": [-15, 0, 15], "uv": [5, 0]},
						{"origin": [3.13354, 16.73995, -2.84178], "size": [1, 3, 1], "pivot": [3.73354, 17.73995, -2.44178], "rotation": [-15, 0, 15], "uv": [0, 55]},
						{"origin": [3.13354, 16.73995, -1.84178], "size": [0, 1, 1], "pivot": [3.73354, 17.73995, -2.44178], "rotation": [-15, 0, 15], "uv": [0, 1]}
					]
				},
				{
					"name": "avdolright_arm",
					"parent": "avdolbody",
					"pivot": [-5, 22, 0],
					"cubes": [
						{"origin": [-8, 12, -2], "size": [4, 12, 4], "uv": [60, 49], "mirror": true},
						{"origin": [-8, 13, -2.25], "size": [4, 1, 1], "uv": [70, 92], "mirror": true},
						{"origin": [-8, 13, 1.25], "size": [4, 1, 1], "uv": [91, 2], "mirror": true},
						{"origin": [-8.25, 13, -2], "size": [1, 1, 4], "uv": [86, 81], "mirror": true},
						{"origin": [-4.75, 13, -2], "size": [1, 1, 4], "uv": [85, 20], "mirror": true},
						{"origin": [-8, 14, -2.35], "size": [4, 1, 1], "uv": [90, 52], "mirror": true},
						{"origin": [-8.35, 14, -2], "size": [1, 1, 4], "uv": [82, 40], "mirror": true},
						{"origin": [-8, 14, 1.35], "size": [4, 1, 1], "uv": [91, 0], "mirror": true},
						{"origin": [-4.65, 14, -2], "size": [1, 1, 4], "uv": [82, 65], "mirror": true},
						{"origin": [-8, 15, -2.45], "size": [4, 1, 1], "uv": [56, 15], "mirror": true},
						{"origin": [-8.45, 15, -2], "size": [1, 1, 4], "uv": [78, 30], "mirror": true},
						{"origin": [-8, 15, 1.45], "size": [4, 1, 1], "uv": [90, 50], "mirror": true},
						{"origin": [-4.55, 15, -2], "size": [1, 1, 4], "uv": [82, 35], "mirror": true},
						{"origin": [-8, 20.22145, -2.82625], "size": [4, 2, 1], "pivot": [-6, 21.22145, -2.32625], "rotation": [7.5, 0, 0], "uv": [4, 90], "mirror": true},
						{"origin": [-8, 22.07382, -2.82625], "size": [4, 2, 1], "pivot": [-6, 23.07382, -2.32625], "rotation": [-7.5, 0, 0], "uv": [70, 89], "mirror": true},
						{"origin": [-8.82625, 22.07382, -2], "size": [1, 2, 4], "pivot": [-8.32625, 23.07382, 0], "rotation": [0, 0, 7.5], "uv": [22, 82], "mirror": true},
						{"origin": [-8.82625, 20.22145, -2], "size": [1, 2, 4], "pivot": [-8.32625, 21.22145, 0], "rotation": [0, 0, -7.5], "uv": [12, 82], "mirror": true},
						{"origin": [-8, 23.5, -2], "size": [4, 1, 4], "pivot": [-6, 24, 0], "rotation": [0, 0, -2.5], "uv": [0, 71], "mirror": true},
						{"origin": [-8, 20.22145, 1.82625], "size": [4, 2, 1], "pivot": [-6, 21.22145, 2.32625], "rotation": [-7.5, 0, 0], "uv": [89, 9], "mirror": true},
						{"origin": [-8, 22.07382, 1.82625], "size": [4, 2, 1], "pivot": [-6, 23.07382, 2.32625], "rotation": [7.5, 0, 0], "uv": [88, 70], "mirror": true},
						{"origin": [-4.17375, 22.07382, -2], "size": [1, 2, 4], "pivot": [-3.67375, 23.07382, 0], "rotation": [0, 0, -7.5], "uv": [79, 18], "mirror": true},
						{"origin": [-4.17375, 20.22145, -2], "size": [1, 2, 4], "pivot": [-3.67375, 21.22145, 0], "rotation": [0, 0, 7.5], "uv": [6, 79], "mirror": true},
						{"origin": [-8, 18.66734, -2.68815], "size": [4, 1, 1], "pivot": [-6, 18.66734, -2.18815], "rotation": [12.5, 0, 0], "uv": [92, 68], "mirror": true},
						{"origin": [-8, 16.93904, -2.94178], "size": [4, 2, 1], "pivot": [-6, 17.93904, -2.44178], "rotation": [-15, 0, 0], "uv": [88, 65], "mirror": true},
						{"origin": [-9, 15.93904, -3.29178], "size": [6, 1, 1], "pivot": [-6, 17.93904, -2.44178], "rotation": [-15, 0, 0], "uv": [74, 76], "mirror": true},
						{"origin": [-9.31237, 15.92201, -3], "size": [1, 1, 6], "pivot": [-8.31237, 18.42201, 0], "rotation": [0, 0, 15], "uv": [28, 70], "mirror": true},
						{"origin": [-8, 19.4272, -2.90459], "size": [4, 1, 1], "pivot": [-6, 19.4272, -2.40459], "rotation": [-12.5, 0, 0], "uv": [92, 81], "mirror": true},
						{"origin": [-8, 16.93904, 1.94178], "size": [4, 2, 1], "pivot": [-6, 17.93904, 2.44178], "rotation": [15, 0, 0], "uv": [85, 5], "mirror": true},
						{"origin": [-8, 18.66734, 1.68815], "size": [4, 1, 1], "pivot": [-6, 18.66734, 2.18815], "rotation": [-12.5, 0, 0], "uv": [92, 55], "mirror": true},
						{"origin": [-8, 19.4272, 1.90459], "size": [4, 1, 1], "pivot": [-6, 19.4272, 2.40459], "rotation": [12.5, 0, 0], "uv": [92, 57], "mirror": true},
						{"origin": [-9, 15.93904, 2.29178], "size": [6, 1, 1], "pivot": [-6, 17.93904, 2.44178], "rotation": [15, 0, 0], "uv": [76, 63], "mirror": true},
						{"origin": [-8.90459, 19.4272, -2], "size": [1, 1, 4], "pivot": [-8.40459, 19.4272, 0], "rotation": [0, 0, 12.5], "uv": [86, 86], "mirror": true},
						{"origin": [-8.68815, 18.66734, -2], "size": [1, 1, 4], "pivot": [-8.18815, 18.66734, 0], "rotation": [0, 0, -12.5], "uv": [86, 55], "mirror": true},
						{"origin": [-8.81237, 16.92201, -2], "size": [1, 2, 4], "pivot": [-8.31237, 18.42201, 0], "rotation": [0, 0, 15], "uv": [78, 78], "mirror": true},
						{"origin": [-3.68763, 15.92201, -3], "size": [1, 1, 6], "pivot": [-3.68763, 18.42201, 0], "rotation": [0, 0, -15], "uv": [68, 69], "mirror": true},
						{"origin": [-4.18763, 16.92201, -2], "size": [1, 2, 4], "pivot": [-3.68763, 18.42201, 0], "rotation": [0, 0, -15], "uv": [48, 78], "mirror": true},
						{"origin": [-4.31185, 18.66734, -2], "size": [1, 1, 4], "pivot": [-3.81185, 18.66734, 0], "rotation": [0, 0, 12.5], "uv": [85, 26], "mirror": true},
						{"origin": [-4.09541, 19.4272, -2], "size": [1, 1, 4], "pivot": [-3.59541, 19.4272, 0], "rotation": [0, 0, -12.5], "uv": [46, 85], "mirror": true},
						{"origin": [-8.86646, 16.73995, -2.84178], "size": [1, 3, 1], "pivot": [-8.26646, 17.73995, -2.44178], "rotation": [-15, 0, 15], "uv": [64, 10], "mirror": true},
						{"origin": [-7.86646, 16.73995, -2.84178], "size": [1, 1, 0], "pivot": [-8.26646, 17.73995, -2.44178], "rotation": [-15, 0, 15], "uv": [0, 17], "mirror": true},
						{"origin": [-8.86646, 16.73995, -1.84178], "size": [0, 1, 1], "pivot": [-8.26646, 17.73995, -2.44178], "rotation": [-15, 0, 15], "uv": [5, 1], "mirror": true},
						{"origin": [-7.86646, 16.73995, 2.84178], "size": [1, 1, 0], "pivot": [-8.26646, 17.73995, 2.44178], "rotation": [15, 0, 15], "uv": [0, 16], "mirror": true},
						{"origin": [-8.86646, 16.73995, 1.84178], "size": [1, 3, 1], "pivot": [-8.26646, 17.73995, 2.44178], "rotation": [15, 0, 15], "uv": [60, 49], "mirror": true},
						{"origin": [-8.86646, 16.73995, 0.84178], "size": [0, 1, 1], "pivot": [-8.26646, 17.73995, 2.44178], "rotation": [15, 0, 15], "uv": [5, 0], "mirror": true},
						{"origin": [-5.13354, 16.73995, 2.84178], "size": [1, 1, 0], "pivot": [-3.73354, 17.73995, 2.44178], "rotation": [15, 0, -15], "uv": [0, 0], "mirror": true},
						{"origin": [-4.13354, 16.73995, 1.84178], "size": [1, 3, 1], "pivot": [-3.73354, 17.73995, 2.44178], "rotation": [15, 0, -15], "uv": [48, 10], "mirror": true},
						{"origin": [-3.13354, 16.73995, 0.84178], "size": [0, 1, 1], "pivot": [-3.73354, 17.73995, 2.44178], "rotation": [15, 0, -15], "uv": [0, 0], "mirror": true},
						{"origin": [-5.13354, 16.73995, -2.84178], "size": [1, 1, 0], "pivot": [-3.73354, 17.73995, -2.44178], "rotation": [-15, 0, -15], "uv": [5, 0], "mirror": true},
						{"origin": [-4.13354, 16.73995, -2.84178], "size": [1, 3, 1], "pivot": [-3.73354, 17.73995, -2.44178], "rotation": [-15, 0, -15], "uv": [0, 55], "mirror": true},
						{"origin": [-3.13354, 16.73995, -1.84178], "size": [0, 1, 1], "pivot": [-3.73354, 17.73995, -2.44178], "rotation": [-15, 0, -15], "uv": [0, 1], "mirror": true}
					]
				},
				{
					"name": "avdolleft_leg",
					"parent": "avdolbody",
					"pivot": [2, 12, 0],
					"cubes": [
						{"origin": [0, 0, -2], "size": [4, 12, 4], "uv": [0, 55]},
						{"origin": [0, 0, -4], "size": [4, 2, 2], "uv": [16, 58]},
						{"origin": [0, -0.25, -4], "size": [4, 1, 6], "uv": [62, 38]},
						{"origin": [0, 0, 1.25], "size": [4, 2, 1], "uv": [6, 76]},
						{"origin": [3.25, 0, -2], "size": [1, 2, 4], "uv": [28, 78]},
						{"origin": [-0.25, 0, -2], "size": [1, 2, 4], "uv": [76, 69]},
						{"origin": [0, 1.93787, 1.38264], "size": [4, 3, 1], "pivot": [2, 3.43787, 1.88264], "rotation": [-5, 0, 0], "uv": [88, 35]},
						{"origin": [0, 1.93787, -2.38264], "size": [4, 3, 1], "pivot": [2, 3.43787, -1.88264], "rotation": [5, 0, 0], "uv": [88, 31]},
						{"origin": [3.43192, 2.0667, -2], "size": [1, 3, 4], "pivot": [2.43192, 4.0667, 1.5], "rotation": [0, 0, 5], "uv": [0, 76]},
						{"origin": [-0.43192, 2.0667, -2], "size": [1, 3, 4], "pivot": [1.56808, 4.0667, 1.5], "rotation": [0, 0, -5], "uv": [22, 75]},
						{"origin": [0, 11, -2.7], "size": [2, 1, 1], "uv": [80, 45]},
						{"origin": [0, 11, 1.7], "size": [2, 1, 1], "uv": [74, 78]},
						{"origin": [-0.5, 11, -2], "size": [1, 1, 4], "uv": [34, 83]},
						{"origin": [3.4, 11, -2], "size": [1, 1, 4], "uv": [0, 83]},
						{"origin": [-1, 8.95, -3], "size": [6, 2, 6], "pivot": [2, 9.95, 0], "rotation": [0, 0, -12.5], "uv": [24, 0]},
						{"origin": [-0.75, 5.95, -3], "size": [3, 2, 1], "pivot": [-0.25, 6.9495, 0], "rotation": [0, 0, 12.5], "uv": [82, 55]},
						{"origin": [1.8247, 5.71773, 2.01], "size": [3, 2, 1], "pivot": [4.0747, 6.71723, 0], "rotation": [0, 0, -7.5], "uv": [34, 77]},
						{"origin": [1.8247, 5.71773, -3.01], "size": [3, 2, 1], "pivot": [4.0747, 6.71723, 0], "rotation": [0, 0, -7.5], "uv": [0, 5]},
						{"origin": [4.0747, 5.71673, -2.5], "size": [1, 2, 5], "pivot": [4.0747, 6.71723, 0], "rotation": [0, 0, -7.5], "uv": [71, 30]},
						{"origin": [-0.75, 5.95, 2], "size": [3, 2, 1], "pivot": [-0.25, 6.9495, 0], "rotation": [0, 0, 12.5], "uv": [16, 67]},
						{"origin": [-1, 5.949, -2.5], "size": [1, 2, 5], "pivot": [-0.25, 6.9495, 0], "rotation": [0, 0, 12.5], "uv": [48, 28]},
						{"origin": [-0.4, 10, -2], "size": [1, 1, 4], "uv": [82, 71]},
						{"origin": [2, 11.25, -2], "size": [2, 1, 4], "uv": [76, 49]},
						{"origin": [0, 11.35, -2], "size": [2, 1, 4], "uv": [8, 28]},
						{"origin": [2, 11, -2.4], "size": [2, 1, 1], "uv": [79, 24]},
						{"origin": [2, 10, -2.4], "size": [1, 1, 1], "uv": [47, 22]},
						{"origin": [2, 10, 1.4], "size": [1, 1, 1], "uv": [47, 17]},
						{"origin": [0, 10, -2.4], "size": [2, 1, 1], "uv": [39, 17]},
						{"origin": [0, 10, 1.4], "size": [2, 1, 1], "uv": [22, 35]},
						{"origin": [2, 11, 1.4], "size": [2, 1, 1], "uv": [52, 35]},
						{"origin": [3.67241, 7.35119, -2], "size": [1, 3, 4], "pivot": [4.17241, 8.35119, 0], "rotation": [0, 0, -5], "uv": [38, 76]},
						{"origin": [3.38647, 4.57909, -2], "size": [1, 3, 4], "pivot": [3.88647, 6.07909, 0], "rotation": [0, 0, 15], "uv": [12, 75]},
						{"origin": [-0.38647, 4.57909, -2], "size": [1, 3, 4], "pivot": [0.11353, 6.07909, 0], "rotation": [0, 0, -15], "uv": [50, 71]},
						{"origin": [0, 7.34738, -2.58525], "size": [4, 3, 1], "pivot": [2, 9.34738, -2.08525], "rotation": [-5, 0, 0], "uv": [56, 88]},
						{"origin": [0, 4.59613, -2.25706], "size": [4, 3, 1], "pivot": [2, 5.59613, -1.75706], "rotation": [15, 0, 0], "uv": [16, 88]},
						{"origin": [0, 4.59613, 1.25706], "size": [4, 3, 1], "pivot": [2, 5.59613, 1.75706], "rotation": [-15, 0, 0], "uv": [22, 31]},
						{"origin": [-0.67241, 7.35119, -2], "size": [1, 3, 4], "pivot": [-0.17241, 8.35119, 0], "rotation": [0, 0, 5], "uv": [76, 37]},
						{"origin": [0, 7.34738, 1.58525], "size": [4, 3, 1], "pivot": [2, 9.34738, 2.08525], "rotation": [5, 0, 0], "uv": [88, 40]}
					]
				},
				{
					"name": "avdolright_leg",
					"parent": "avdolbody",
					"pivot": [-2, 12, 0],
					"cubes": [
						{"origin": [-4, 0, -2], "size": [4, 12, 4], "uv": [0, 55], "mirror": true},
						{"origin": [-4, 0, -4], "size": [4, 2, 2], "uv": [16, 58], "mirror": true},
						{"origin": [-4, -0.25, -4], "size": [4, 1, 6], "uv": [62, 38], "mirror": true},
						{"origin": [-4, 0, 1.25], "size": [4, 2, 1], "uv": [6, 76], "mirror": true},
						{"origin": [-4.25, 0, -2], "size": [1, 2, 4], "uv": [28, 78], "mirror": true},
						{"origin": [-0.75, 0, -2], "size": [1, 2, 4], "uv": [76, 69], "mirror": true},
						{"origin": [-4, 1.93787, 1.38264], "size": [4, 3, 1], "pivot": [-2, 3.43787, 1.88264], "rotation": [-5, 0, 0], "uv": [88, 35], "mirror": true},
						{"origin": [-4, 1.93787, -2.38264], "size": [4, 3, 1], "pivot": [-2, 3.43787, -1.88264], "rotation": [5, 0, 0], "uv": [88, 31], "mirror": true},
						{"origin": [-4.43192, 2.0667, -2], "size": [1, 3, 4], "pivot": [-2.43192, 4.0667, 1.5], "rotation": [0, 0, -5], "uv": [0, 76], "mirror": true},
						{"origin": [-0.56808, 2.0667, -2], "size": [1, 3, 4], "pivot": [-1.56808, 4.0667, 1.5], "rotation": [0, 0, 5], "uv": [22, 75], "mirror": true},
						{"origin": [-2, 11, -2.7], "size": [2, 1, 1], "uv": [80, 45], "mirror": true},
						{"origin": [-2, 11, 1.7], "size": [2, 1, 1], "uv": [74, 78], "mirror": true},
						{"origin": [-0.5, 11, -2], "size": [1, 1, 4], "uv": [34, 83], "mirror": true},
						{"origin": [-4.4, 11, -2], "size": [1, 1, 4], "uv": [0, 83], "mirror": true},
						{"origin": [-5, 8.95, -3], "size": [6, 2, 6], "pivot": [-2, 9.95, 0], "rotation": [0, 0, 12.5], "uv": [24, 0], "mirror": true},
						{"origin": [-2.25, 5.95, -3], "size": [3, 2, 1], "pivot": [0.25, 6.9495, 0], "rotation": [0, 0, -12.5], "uv": [82, 55], "mirror": true},
						{"origin": [-4.8247, 5.71773, 2.01], "size": [3, 2, 1], "pivot": [-4.0747, 6.71723, 0], "rotation": [0, 0, 7.5], "uv": [34, 77], "mirror": true},
						{"origin": [-4.8247, 5.71773, -3.01], "size": [3, 2, 1], "pivot": [-4.0747, 6.71723, 0], "rotation": [0, 0, 7.5], "uv": [0, 5], "mirror": true},
						{"origin": [-5.0747, 5.71673, -2.5], "size": [1, 2, 5], "pivot": [-4.0747, 6.71723, 0], "rotation": [0, 0, 7.5], "uv": [71, 30], "mirror": true},
						{"origin": [-2.25, 5.95, 2], "size": [3, 2, 1], "pivot": [0.25, 6.9495, 0], "rotation": [0, 0, -12.5], "uv": [16, 67], "mirror": true},
						{"origin": [0, 5.949, -2.5], "size": [1, 2, 5], "pivot": [0.25, 6.9495, 0], "rotation": [0, 0, -12.5], "uv": [48, 28], "mirror": true},
						{"origin": [-0.6, 10, -2], "size": [1, 1, 4], "uv": [82, 71], "mirror": true},
						{"origin": [-4, 11.25, -2], "size": [2, 1, 4], "uv": [76, 49], "mirror": true},
						{"origin": [-2, 11.35, -2], "size": [2, 1, 4], "uv": [8, 28], "mirror": true},
						{"origin": [-4, 11, -2.4], "size": [2, 1, 1], "uv": [79, 24], "mirror": true},
						{"origin": [-3, 10, -2.4], "size": [1, 1, 1], "uv": [47, 22], "mirror": true},
						{"origin": [-3, 10, 1.4], "size": [1, 1, 1], "uv": [47, 17], "mirror": true},
						{"origin": [-2, 10, -2.4], "size": [2, 1, 1], "uv": [39, 17], "mirror": true},
						{"origin": [-2, 10, 1.4], "size": [2, 1, 1], "uv": [22, 35], "mirror": true},
						{"origin": [-4, 11, 1.4], "size": [2, 1, 1], "uv": [52, 35], "mirror": true},
						{"origin": [-4.67241, 7.35119, -2], "size": [1, 3, 4], "pivot": [-4.17241, 8.35119, 0], "rotation": [0, 0, 5], "uv": [38, 76], "mirror": true},
						{"origin": [-4.38647, 4.57909, -2], "size": [1, 3, 4], "pivot": [-3.88647, 6.07909, 0], "rotation": [0, 0, -15], "uv": [12, 75], "mirror": true},
						{"origin": [-0.61353, 4.57909, -2], "size": [1, 3, 4], "pivot": [-0.11353, 6.07909, 0], "rotation": [0, 0, 15], "uv": [50, 71], "mirror": true},
						{"origin": [-4, 7.34738, -2.58525], "size": [4, 3, 1], "pivot": [-2, 9.34738, -2.08525], "rotation": [-5, 0, 0], "uv": [56, 88], "mirror": true},
						{"origin": [-4, 4.59613, -2.25706], "size": [4, 3, 1], "pivot": [-2, 5.59613, -1.75706], "rotation": [15, 0, 0], "uv": [16, 88], "mirror": true},
						{"origin": [-4, 4.59613, 1.25706], "size": [4, 3, 1], "pivot": [-2, 5.59613, 1.75706], "rotation": [-15, 0, 0], "uv": [22, 31], "mirror": true},
						{"origin": [-0.32759, 7.35119, -2], "size": [1, 3, 4], "pivot": [0.17241, 8.35119, 0], "rotation": [0, 0, -5], "uv": [76, 37], "mirror": true},
						{"origin": [-4, 7.34738, 1.58525], "size": [4, 3, 1], "pivot": [-2, 9.34738, 2.08525], "rotation": [5, 0, 0], "uv": [88, 40], "mirror": true}
					]
				},
				{
					"name": "Body",
					"pivot": [0, 22, 0]
				},
				{
					"name": "head",
					"parent": "Body",
					"pivot": [0, 25.75, 0],
					"rotation": [5, 0, 0],
					"cubes": [
						{"origin": [-3.5, 25.75, -3.75], "size": [7, 6, 7], "uv": [0, 113]},
						{"origin": [-1, 31.46419, 2.3004], "size": [2, 2, 3], "pivot": [-3, 31.96419, 4.3004], "rotation": [20, 0, 0], "uv": [33, 142]},
						{"origin": [-1, 31.78267, -0.62538], "size": [2, 2, 3], "pivot": [-3, 32.28267, 4.37462], "rotation": [27.5, 0, 0], "uv": [40, 108]},
						{"origin": [-1.001, 31.5895, 4.65324], "size": [2, 2, 2], "pivot": [0, 33.0895, 5.65324], "rotation": [-7.5, 0, 0], "uv": [44, 121]},
						{"origin": [-0.999, 30.85697, 5.92203], "size": [2, 2, 2], "pivot": [0, 32.35697, 6.92203], "rotation": [-52.5, 0, 0], "uv": [44, 101]},
						{"origin": [1, 30, -4.75], "size": [3, 1, 1], "pivot": [2.5, 30.25, -4.25], "rotation": [0, -30, -12.5], "uv": [44, 105]},
						{"origin": [-4, 30, -4.75], "size": [3, 1, 1], "pivot": [-2.5, 30.25, -4.25], "rotation": [0, 30, 12.5], "uv": [25, 101]},
						{"origin": [-2.5, 28, -4.75], "size": [5, 3, 1], "uv": [36, 132]},
						{"origin": [-2, 28, -7.5], "size": [4, 2, 3], "pivot": [0, 28, -6], "rotation": [5, 0, 0], "uv": [30, 101]},
						{"origin": [-1.5, 27.17992, -8.93125], "size": [3, 2, 2], "pivot": [0.5, 28.17992, -8.43125], "rotation": [15, 0, 0], "uv": [16, 144]},
						{"origin": [-1, 26.51577, -10.10336], "size": [2, 1, 2], "pivot": [0, 27.51577, -9.60336], "rotation": [42.5, 0, 0], "uv": [26, 145]},
						{"origin": [-0.5, 24.64006, -11.56973], "size": [1, 1, 1], "pivot": [-1, 27.39006, -11.06973], "rotation": [52.5, 0, 0], "uv": [20, 134]}
					]
				},
				{
					"name": "crest",
					"parent": "head",
					"pivot": [0, 28.42714, 8.51331],
					"rotation": [-12.5, 0, 0],
					"cubes": [
						{"origin": [-1, 27.21419, 4.3004], "size": [2, 2, 2], "pivot": [-3, 27.71419, 5.3004], "rotation": [20, 0, 0], "uv": [12, 137]},
						{"origin": [-1, 27.55393, 2.49701], "size": [2, 2, 2], "pivot": [-3, 28.05393, 5.49701], "rotation": [32.5, 0, 0], "uv": [15, 126]},
						{"origin": [-1.001, 27.3395, 5.65324], "size": [2, 2, 2], "pivot": [0, 28.8395, 6.65324], "rotation": [-7.5, 0, 0], "uv": [43, 117]},
						{"origin": [-0.999, 26.59266, 6.82555], "size": [2, 2, 2], "pivot": [0, 28.09266, 7.82555], "rotation": [-57.5, 0, 0], "uv": [43, 142]}
					]
				},
				{
					"name": "Jaw",
					"parent": "head",
					"pivot": [0, 28.09101, -3.81047],
					"cubes": [
						{"origin": [-2.5, 26, -4.75], "size": [5, 2, 1], "uv": [52, 134]},
						{"origin": [-2, 26, -7.5], "size": [4, 2, 3], "pivot": [0, 28, -6], "rotation": [5, 0, 0], "uv": [47, 147]},
						{"origin": [-1.5, 26.17992, -8.93125], "size": [3, 1, 2], "pivot": [0.5, 28.17992, -8.43125], "rotation": [15, 0, 0], "uv": [49, 144]},
						{"origin": [-1, 25.51577, -10.10336], "size": [2, 1, 2], "pivot": [0, 27.51577, -9.60336], "rotation": [42.5, 0, 0], "uv": [51, 141]}
					]
				},
				{
					"name": "torso",
					"parent": "Body",
					"pivot": [0, 26, 0],
					"cubes": [
						{"origin": [-4, 13, -2], "size": [8, 6, 4], "uv": [24, 122]},
						{"origin": [3.6, 13.25, -1.5], "size": [1, 2, 1], "pivot": [4.1, 14.25, -1], "rotation": [0, 0, 32.5], "uv": [48, 125]},
						{"origin": [3.6, 13.5, 0.5], "size": [1, 2, 1], "pivot": [4.1, 14.5, 1], "rotation": [0, 0, 32.5], "uv": [24, 149]},
						{"origin": [-4.6, 13.5, 0.5], "size": [1, 2, 1], "pivot": [-4.1, 14.5, 1], "rotation": [0, 0, -32.5], "uv": [16, 149]},
						{"origin": [-4.6, 13.25, -1.5], "size": [1, 2, 1], "pivot": [-4.1, 14.25, -1], "rotation": [0, 0, -32.5], "uv": [20, 149]},
						{"origin": [2.6, 12.75, -2.5], "size": [1, 2, 1], "pivot": [3.1, 13.75, -2], "rotation": [32.5, 0, 0], "uv": [12, 149]},
						{"origin": [-3.4, 13, -2.5], "size": [1, 2, 1], "pivot": [-2.9, 14, -2], "rotation": [32.5, 0, 0], "uv": [47, 137]},
						{"origin": [-0.4, 13.25, -2.5], "size": [1, 2, 1], "pivot": [0.1, 14.25, -2], "rotation": [32.5, 0, 0], "uv": [16, 141]},
						{"origin": [-3.4, 13, 1.5], "size": [1, 2, 1], "pivot": [-2.9, 14, 2], "rotation": [-32.5, 0, 0], "uv": [21, 117]},
						{"origin": [-0.4, 13.25, 1.5], "size": [1, 2, 1], "pivot": [0.1, 14.25, 2], "rotation": [-32.5, 0, 0], "uv": [25, 103]},
						{"origin": [2.6, 12.75, 1.5], "size": [1, 2, 1], "pivot": [3.1, 13.75, 2], "rotation": [-32.5, 0, 0], "uv": [38, 119]}
					]
				},
				{
					"name": "UpperTorso",
					"parent": "torso",
					"pivot": [0, 19, 0],
					"cubes": [
						{"origin": [-5, 19, -2.5], "size": [10, 7, 5], "uv": [0, 101]}
					]
				},
				{
					"name": "left_arm",
					"parent": "Body",
					"pivot": [6.5, 24, 0],
					"cubes": [
						{"origin": [5, 20, -2.5], "size": [5, 6, 5], "uv": [25, 108]}
					]
				},
				{
					"name": "lowerarm",
					"parent": "left_arm",
					"pivot": [7.5, 21, 0],
					"cubes": [
						{"origin": [5.5, 13, -2], "size": [4, 8, 4], "uv": [0, 137]},
						{"origin": [9.1, 15.25, 0], "size": [1, 2, 1], "pivot": [9.6, 16.25, 0.5], "rotation": [0, 0, 32.5], "uv": [41, 150]},
						{"origin": [9.1, 16.25, -1.5], "size": [1, 2, 1], "pivot": [9.6, 17.25, -1], "rotation": [0, 0, 32.5], "uv": [49, 140]},
						{"origin": [8.1, 15.25, -2.5], "size": [1, 2, 1], "pivot": [8.6, 16.25, -2], "rotation": [32.5, 0, 0], "uv": [48, 134]},
						{"origin": [6.1, 16, -2.5], "size": [1, 2, 1], "pivot": [6.6, 17, -2], "rotation": [32.5, 0, 0], "uv": [48, 131]},
						{"origin": [6.1, 16, 1.5], "size": [1, 2, 1], "pivot": [6.6, 17, 2], "rotation": [-32.5, 0, 0], "uv": [48, 128]},
						{"origin": [8.1, 15.25, 1.5], "size": [1, 2, 1], "pivot": [8.6, 16.25, 2], "rotation": [-32.5, 0, 0], "uv": [28, 149]},
						{"origin": [4.9, 16.25, 0.5], "size": [1, 2, 1], "pivot": [5.4, 17.25, 1], "rotation": [0, 0, -32.5], "uv": [49, 112]},
						{"origin": [4.9, 15.5, -1.5], "size": [1, 2, 1], "pivot": [5.4, 16.5, -1], "rotation": [0, 0, -32.5], "uv": [49, 115]}
					]
				},
				{
					"name": "right_arm",
					"parent": "Body",
					"pivot": [-6.5, 24, 0],
					"cubes": [
						{"origin": [-10, 20, -2.5], "size": [5, 6, 5], "uv": [25, 108], "mirror": true}
					]
				},
				{
					"name": "lowerarm2",
					"parent": "right_arm",
					"pivot": [-7.5, 21, 0],
					"cubes": [
						{"origin": [-9.5, 13, -2], "size": [4, 8, 4], "uv": [0, 137], "mirror": true},
						{"origin": [-10.1, 15.25, 0], "size": [1, 2, 1], "pivot": [-9.6, 16.25, 0.5], "rotation": [0, 0, -32.5], "uv": [41, 150], "mirror": true},
						{"origin": [-10.1, 16.25, -1.5], "size": [1, 2, 1], "pivot": [-9.6, 17.25, -1], "rotation": [0, 0, -32.5], "uv": [49, 140], "mirror": true},
						{"origin": [-9.1, 15.25, -2.5], "size": [1, 2, 1], "pivot": [-8.6, 16.25, -2], "rotation": [32.5, 0, 0], "uv": [48, 134], "mirror": true},
						{"origin": [-7.1, 16, -2.5], "size": [1, 2, 1], "pivot": [-6.6, 17, -2], "rotation": [32.5, 0, 0], "uv": [48, 131], "mirror": true},
						{"origin": [-7.1, 16, 1.5], "size": [1, 2, 1], "pivot": [-6.6, 17, 2], "rotation": [-32.5, 0, 0], "uv": [48, 128], "mirror": true},
						{"origin": [-9.1, 15.25, 1.5], "size": [1, 2, 1], "pivot": [-8.6, 16.25, 2], "rotation": [-32.5, 0, 0], "uv": [28, 149], "mirror": true},
						{"origin": [-5.9, 16.25, 0.5], "size": [1, 2, 1], "pivot": [-5.4, 17.25, 1], "rotation": [0, 0, 32.5], "uv": [49, 112], "mirror": true},
						{"origin": [-5.9, 15.5, -1.5], "size": [1, 2, 1], "pivot": [-5.4, 16.5, -1], "rotation": [0, 0, 32.5], "uv": [49, 115], "mirror": true}
					]
				},
				{
					"name": "left_leg",
					"parent": "Body",
					"pivot": [2, 13, 0],
					"cubes": [
						{"origin": [-0.5, 7, -2.5], "size": [5, 6, 5], "uv": [0, 126]},
						{"origin": [4.4, 8.25, -1.5], "size": [1, 3, 1], "pivot": [4.9, 9.75, -1], "rotation": [0, 0, 32.5], "uv": [0, 137]},
						{"origin": [4.4, 9.75, 1], "size": [1, 3, 1], "pivot": [4.9, 11.25, 1.5], "rotation": [0, 0, 32.5], "uv": [32, 132]},
						{"origin": [-1.4, 9.75, -1.75], "size": [1, 3, 1], "pivot": [-0.9, 11.25, -1.25], "rotation": [0, 0, -32.5], "uv": [0, 126]},
						{"origin": [-1.4, 8.25, 0.5], "size": [1, 3, 1], "pivot": [-0.9, 9.75, 1], "rotation": [0, 0, -32.5], "uv": [20, 130]},
						{"origin": [2.75, 8.25, -3.35], "size": [1, 3, 1], "pivot": [3.25, 9.75, -2.85], "rotation": [32.5, 0, 0], "uv": [21, 113]},
						{"origin": [0.25, 8.5, -3.35], "size": [1, 3, 1], "pivot": [0.75, 10, -2.85], "rotation": [32.5, 0, 0], "uv": [3, 116]},
						{"origin": [2.75, 8.5, 2.35], "size": [1, 3, 1], "pivot": [3.25, 10, 2.85], "rotation": [-32.5, 0, 0], "uv": [0, 101]},
						{"origin": [0.25, 9.5, 2.35], "size": [1, 3, 1], "pivot": [0.75, 11, 2.85], "rotation": [-32.5, 0, 0], "uv": [0, 113]}
					]
				},
				{
					"name": "lowerleg",
					"parent": "left_leg",
					"pivot": [2, 8, 0],
					"cubes": [
						{"origin": [0, 0, -2], "size": [4, 8, 4], "uv": [20, 132]},
						{"origin": [3.9, 4.1, -1.5], "size": [1, 3, 1], "pivot": [4.4, 5.6, -1], "rotation": [0, 0, 32.5], "uv": [4, 149]},
						{"origin": [2.5, 4, -2.85], "size": [1, 3, 1], "pivot": [3, 5.5, -2.35], "rotation": [32.5, 0, 0], "uv": [47, 107]},
						{"origin": [0.5, 5, -2.85], "size": [1, 3, 1], "pivot": [1, 6.5, -2.35], "rotation": [32.5, 0, 0], "uv": [46, 146]},
						{"origin": [0.5, 5.25, 1.85], "size": [1, 3, 1], "pivot": [1, 6.75, 2.35], "rotation": [-32.5, 0, 0], "uv": [34, 147]},
						{"origin": [2.5, 4, 1.85], "size": [1, 3, 1], "pivot": [3, 5.5, 2.35], "rotation": [-32.5, 0, 0], "uv": [38, 147]},
						{"origin": [3.9, 5.5, 0], "size": [1, 3, 1], "pivot": [4.4, 7, 0.5], "rotation": [0, 0, 32.5], "uv": [0, 149]},
						{"origin": [-0.9, 4.25, 0.5], "size": [1, 3, 1], "pivot": [-0.4, 5.75, 1], "rotation": [0, 0, -32.5], "uv": [45, 113]},
						{"origin": [-0.9, 5.5, -1.5], "size": [1, 3, 1], "pivot": [-0.4, 7, -1], "rotation": [0, 0, -32.5], "uv": [42, 146]},
						{"origin": [0, 0, -4], "size": [4, 2, 2], "uv": [36, 138]},
						{"origin": [0, 2, -4], "size": [4, 1, 1], "uv": [28, 119]}
					]
				},
				{
					"name": "right_leg",
					"parent": "Body",
					"pivot": [-2, 13, 0],
					"cubes": [
						{"origin": [-4.5, 7, -2.5], "size": [5, 6, 5], "uv": [0, 126], "mirror": true},
						{"origin": [-5.4, 8.25, -1.5], "size": [1, 3, 1], "pivot": [-4.9, 9.75, -1], "rotation": [0, 0, -32.5], "uv": [0, 137], "mirror": true},
						{"origin": [-5.4, 9.75, 1], "size": [1, 3, 1], "pivot": [-4.9, 11.25, 1.5], "rotation": [0, 0, -32.5], "uv": [32, 132], "mirror": true},
						{"origin": [0.4, 9.75, -1.75], "size": [1, 3, 1], "pivot": [0.9, 11.25, -1.25], "rotation": [0, 0, 32.5], "uv": [0, 126], "mirror": true},
						{"origin": [0.4, 8.25, 0.5], "size": [1, 3, 1], "pivot": [0.9, 9.75, 1], "rotation": [0, 0, 32.5], "uv": [20, 130], "mirror": true},
						{"origin": [-3.75, 7.75, -3.35], "size": [1, 3, 1], "pivot": [-3.25, 9.25, -2.85], "rotation": [32.5, 0, 0], "uv": [21, 113], "mirror": true},
						{"origin": [-1.25, 9, -3.35], "size": [1, 3, 1], "pivot": [-0.75, 10.5, -2.85], "rotation": [32.5, 0, 0], "uv": [3, 116], "mirror": true},
						{"origin": [-3.75, 9.25, 2.35], "size": [1, 3, 1], "pivot": [-3.25, 10.75, 2.85], "rotation": [-32.5, 0, 0], "uv": [0, 101], "mirror": true},
						{"origin": [-1.25, 8, 2.35], "size": [1, 3, 1], "pivot": [-0.75, 9.5, 2.85], "rotation": [-32.5, 0, 0], "uv": [0, 113], "mirror": true}
					]
				},
				{
					"name": "lowerleg2",
					"parent": "right_leg",
					"pivot": [-2, 8, 0],
					"cubes": [
						{"origin": [-4, 0, -2], "size": [4, 8, 4], "uv": [20, 132], "mirror": true},
						{"origin": [-4.9, 4.1, -1.5], "size": [1, 3, 1], "pivot": [-4.4, 5.6, -1], "rotation": [0, 0, -32.5], "uv": [4, 149], "mirror": true},
						{"origin": [-3.5, 4, -2.85], "size": [1, 3, 1], "pivot": [-3, 5.5, -2.35], "rotation": [32.5, 0, 0], "uv": [47, 107], "mirror": true},
						{"origin": [-1.5, 4.75, -2.85], "size": [1, 3, 1], "pivot": [-1, 6.25, -2.35], "rotation": [32.5, 0, 0], "uv": [46, 146], "mirror": true},
						{"origin": [-1.5, 4.75, 1.85], "size": [1, 3, 1], "pivot": [-1, 6.25, 2.35], "rotation": [-32.5, 0, 0], "uv": [34, 147], "mirror": true},
						{"origin": [-3.5, 4, 1.85], "size": [1, 3, 1], "pivot": [-3, 5.5, 2.35], "rotation": [-32.5, 0, 0], "uv": [38, 147], "mirror": true},
						{"origin": [-4.9, 5.5, 0], "size": [1, 3, 1], "pivot": [-4.4, 7, 0.5], "rotation": [0, 0, -32.5], "uv": [0, 149], "mirror": true},
						{"origin": [-0.1, 4.25, 0.5], "size": [1, 3, 1], "pivot": [0.4, 5.75, 1], "rotation": [0, 0, 32.5], "uv": [45, 113], "mirror": true},
						{"origin": [-0.1, 5.5, -1.5], "size": [1, 3, 1], "pivot": [0.4, 7, -1], "rotation": [0, 0, 32.5], "uv": [42, 146], "mirror": true},
						{"origin": [-4, 0, -4], "size": [4, 2, 2], "uv": [36, 138], "mirror": true},
						{"origin": [-4, 2, -4], "size": [4, 1, 1], "uv": [28, 119], "mirror": true}
					]
				}
			]
		}
	]
}